MANIFEST.in
crm_todo_demo.xml
crm_todo_view.xml
setup.py
./__init__.py
./__openerp__.py
./crm_todo.py
i18n/ar.po
i18n/bs.po
i18n/crm_todo.pot
i18n/cs.po
i18n/da.po
i18n/de.po
i18n/en_GB.po
i18n/es.po
i18n/es_CR.po
i18n/et.po
i18n/fi.po
i18n/fr.po
i18n/gu.po
i18n/he.po
i18n/hr.po
i18n/hu.po
i18n/it.po
i18n/ja.po
i18n/ko.po
i18n/lt.po
i18n/mk.po
i18n/mn.po
i18n/nb.po
i18n/nl.po
i18n/pl.po
i18n/pt.po
i18n/pt_BR.po
i18n/ro.po
i18n/ru.po
i18n/sl.po
i18n/sr@latin.po
i18n/sv.po
i18n/tr.po
i18n/zh_CN.po
i18n/zh_TW.po
openerp_crm_todo.egg-info/PKG-INFO
openerp_crm_todo.egg-info/SOURCES.txt
openerp_crm_todo.egg-info/dependency_links.txt
openerp_crm_todo.egg-info/requires.txt
openerp_crm_todo.egg-info/top_level.txt